flaskbb_plugin_proxyfix-1.0.dist-info/DESCRIPTION.rst
flaskbb_plugin_proxyfix-1.0.dist-info/METADATA
flaskbb_plugin_proxyfix-1.0.dist-info/RECORD
flaskbb_plugin_proxyfix-1.0.dist-info/WHEEL
flaskbb_plugin_proxyfix-1.0.dist-info/entry_points.txt
flaskbb_plugin_proxyfix-1.0.dist-info/metadata.json
flaskbb_plugin_proxyfix-1.0.dist-info/top_level.txt
proxyfix/__init__.py
